mypy_boto3_ssmsap/__init__.py
mypy_boto3_ssmsap/__init__.pyi
mypy_boto3_ssmsap/__main__.py
mypy_boto3_ssmsap/client.py
mypy_boto3_ssmsap/client.pyi
mypy_boto3_ssmsap/literals.py
mypy_boto3_ssmsap/literals.pyi
mypy_boto3_ssmsap/paginator.py
mypy_boto3_ssmsap/paginator.pyi
mypy_boto3_ssmsap/py.typed
mypy_boto3_ssmsap/type_defs.py
mypy_boto3_ssmsap/type_defs.pyi
mypy_boto3_ssmsap/version.py
mypy_boto3_ssmsap-1.26.10.dist-info/LICENSE
mypy_boto3_ssmsap-1.26.10.dist-info/METADATA
mypy_boto3_ssmsap-1.26.10.dist-info/WHEEL
mypy_boto3_ssmsap-1.26.10.dist-info/top_level.txt
mypy_boto3_ssmsap-1.26.10.dist-info/RECORD
